naas_python/__init__.py
naas_python/cli.py
naas_python/domains/asset/AssetDomain.py
naas_python/domains/asset/AssetSchema.py
naas_python/domains/asset/adaptors/primary/SDKAssetAdaptor.py
naas_python/domains/asset/adaptors/primary/TyperAssetAdaptor.py
naas_python/domains/asset/adaptors/secondary/NaasAssetAPIAdaptor.py
naas_python/domains/asset/handlers/CLIAssetHandler.py
naas_python/domains/asset/handlers/PythonHandler.py
naas_python/domains/asset/models/Asset.py
naas_python/domains/asset/models/__init__.py
naas_python/domains/registry/RegistryDomain.py
naas_python/domains/registry/RegistrySchema.py
naas_python/domains/registry/adaptors/primary/SDKRegistryAdaptor.py
naas_python/domains/registry/adaptors/primary/TyperRegistryAdaptor.py
naas_python/domains/registry/adaptors/secondary/NaasRegistryAPIAdaptor.py
naas_python/domains/registry/handlers/CLIRegistryHandler.py
naas_python/domains/registry/handlers/PythonHandler.py
naas_python/domains/secret/SecretDomain.py
naas_python/domains/secret/SecretSchema.py
naas_python/domains/secret/adaptors/primary/SDKSecretAdaptor.py
naas_python/domains/secret/adaptors/primary/TyperSecretAdaptor.py
naas_python/domains/secret/adaptors/primary/utils.py
naas_python/domains/secret/adaptors/secondary/NaasSecretAPIAdaptor.py
naas_python/domains/secret/handlers/CLISecretHandler.py
naas_python/domains/secret/handlers/PythonHandler.py
naas_python/domains/secret/models/Secret.py
naas_python/domains/secret/models/__init__.py
naas_python/domains/space/SpaceDomain.py
naas_python/domains/space/SpaceSchema.py
naas_python/domains/space/adaptors/primary/SDKSpaceAdaptor.py
naas_python/domains/space/adaptors/primary/TyperSpaceAdaptor.py
naas_python/domains/space/adaptors/primary/utils.py
naas_python/domains/space/adaptors/secondary/NaasSpaceAPIAdaptor.py
naas_python/domains/space/handlers/CLISpaceHandler.py
naas_python/domains/space/handlers/PythonHandler.py
naas_python/domains/storage/StorageDomain.py
naas_python/domains/storage/StorageSchema.py
naas_python-1.4.4.dist-info/METADATA
naas_python-1.4.4.dist-info/WHEEL
naas_python-1.4.4.dist-info/entry_points.txt
naas_python-1.4.4.dist-info/licenses/LICENSE
naas_python-1.4.4.dist-info/RECORD
