Metadata-Version: 2.4
Name: naas-python
Version: 1.4.4
Summary: Naas Python SDK
License: AGPL
License-File: LICENSE
Author: Maxime Jublou
Author-email: maxime@naas.ai
Requires-Python: >=3.9,<4.0
Classifier: License :: Other/Proprietary License
Classifier: Programming Language :: Python :: 3
Classifier: Programming Language :: Python :: 3.9
Classifier: Programming Language :: Python :: 3.10
Classifier: Programming Language :: Python :: 3.11
Classifier: Programming Language :: Python :: 3.12
Classifier: Programming Language :: Python :: 3.13
Classifier: Programming Language :: Python :: 3.14
Requires-Dist: boto3 (>=1.34.128,<2.0.0)
Requires-Dist: cachetools (>=5.3.1,<6.0.0)
Requires-Dist: grpcio (>=1.60.0,<2.0.0)
Requires-Dist: jinja2 (>=3.0.1,<4.0.0)
Requires-Dist: naas-models (>=1.28.3,<2.0.0)
Requires-Dist: pydantic (<2.9)
Requires-Dist: pydash (>=7.0.7,<8.0.0)
Requires-Dist: requests (>=2.31.0,<3.0.0)
Requires-Dist: typer[all] (>=0.9.0,<0.10.0)
